gptcache/__init__.py
gptcache/client.py
gptcache/config.py
gptcache/core.py
gptcache/report.py
gptcache/session.py
gptcache/adapter/__init__.py
gptcache/adapter/adapter.py
gptcache/adapter/api.py
gptcache/adapter/base.py
gptcache/adapter/diffusers.py
gptcache/adapter/dolly.py
gptcache/adapter/langchain_models.py
gptcache/adapter/llama_cpp.py
gptcache/adapter/minigpt4.py
gptcache/adapter/openai.py
gptcache/adapter/replicate.py
gptcache/adapter/stability_sdk.py
gptcache/embedding/__init__.py
gptcache/embedding/base.py
gptcache/embedding/cohere.py
gptcache/embedding/data2vec.py
gptcache/embedding/fasttext.py
gptcache/embedding/huggingface.py
gptcache/embedding/langchain.py
gptcache/embedding/onnx.py
gptcache/embedding/openai.py
gptcache/embedding/paddlenlp.py
gptcache/embedding/rwkv.py
gptcache/embedding/sbert.py
gptcache/embedding/string.py
gptcache/embedding/timm.py
gptcache/embedding/uform.py
gptcache/embedding/vit.py
gptcache/manager/__init__.py
gptcache/manager/data_manager.py
gptcache/manager/eviction_manager.py
gptcache/manager/factory.py
gptcache/manager/eviction/__init__.py
gptcache/manager/eviction/base.py
gptcache/manager/eviction/distributed_cache.py
gptcache/manager/eviction/manager.py
gptcache/manager/eviction/memory_cache.py
gptcache/manager/eviction/redis_eviction.py
gptcache/manager/object_data/__init__.py
gptcache/manager/object_data/base.py
gptcache/manager/object_data/local_storage.py
gptcache/manager/object_data/manager.py
gptcache/manager/object_data/s3_storage.py
gptcache/manager/scalar_data/__init__.py
gptcache/manager/scalar_data/base.py
gptcache/manager/scalar_data/dynamo_storage.py
gptcache/manager/scalar_data/manager.py
gptcache/manager/scalar_data/mongo.py
gptcache/manager/scalar_data/redis_storage.py
gptcache/manager/scalar_data/sql_storage.py
gptcache/manager/vector_data/__init__.py
gptcache/manager/vector_data/base.py
gptcache/manager/vector_data/chroma.py
gptcache/manager/vector_data/docarray_index.py
gptcache-0.1.42.dist-info/LICENSE
gptcache-0.1.42.dist-info/METADATA
gptcache-0.1.42.dist-info/WHEEL
gptcache-0.1.42.dist-info/entry_points.txt
gptcache-0.1.42.dist-info/top_level.txt
gptcache-0.1.42.dist-info/RECORD
