Metadata-Version: 2.1
Name: gptcache
Version: 0.1.42
Summary: GPTCache, a powerful caching library that can be used to speed up and lower the cost of chat applications that rely on the LLM service. GPTCache works as a memcache for AIGC applications, similar to how Redis works for traditional applications.
Home-page: https://github.com/zilliztech/GPTCache
Author: SimFG
Author-email: bang.fu@zilliz.com
License: https://opensource.org/license/mit/
Requires-Python: >=3.8.1
License-File: LICENSE
Requires-Dist: numpy
Requires-Dist: cachetools
Requires-Dist: requests
